htknx/__init__.py
htknx/__main__.py
htknx/__version__.py
htknx/config.py
htknx/config_validation.py
htknx/htdatapoint.py
htknx/htfaultnotification.py
htknx/htknx-template.yaml
htknx/htknx.yaml
htknx/logging.conf
htknx-0.2.0.dist-info/LICENSE
htknx-0.2.0.dist-info/METADATA
htknx-0.2.0.dist-info/WHEEL
htknx-0.2.0.dist-info/entry_points.txt
htknx-0.2.0.dist-info/top_level.txt
htknx-0.2.0.dist-info/RECORD
