Metadata-Version: 2.1
Name: htknx
Version: 0.2.0
Summary: Heliotherm heat pump KNX gateway
Home-page: https://github.com/dstrigl/htknx
Author: Daniel Strigl
License: GNU General Public License v3
Keywords: python python3 heatpump Heliotherm knx bus gateway
Platform: Linux
Classifier: Development Status :: 4 - Beta
Classifier: Intended Audience :: Developers
Classifier: Intended Audience :: Information Technology
Classifier: Intended Audience :: Science/Research
Classifier: Intended Audience :: Manufacturing
Classifier: License :: OSI Approved :: GNU General Public License v3 (GPLv3)
Classifier: Programming Language :: Python
Classifier: Programming Language :: Python :: 3
Classifier: Programming Language :: Python :: 3.7
Classifier: Programming Language :: Python :: 3.8
Classifier: Natural Language :: English
Classifier: Operating System :: POSIX
Classifier: Operating System :: POSIX :: Linux
Classifier: Topic :: Communications
Classifier: Topic :: Home Automation
Classifier: Topic :: Scientific/Engineering
Classifier: Topic :: Software Development :: Embedded Systems
Classifier: Topic :: Terminals :: Serial
Requires-Dist: htheatpump (==1.3.1)
Requires-Dist: xknx (==0.16.1)
Provides-Extra: dev
Requires-Dist: mypy (==0.800) ; extra == 'dev'
Requires-Dist: coverage (==5.4) ; extra == 'dev'
Requires-Dist: pytest (==6.2.2) ; extra == 'dev'
Requires-Dist: pytest-mypy (==0.8.0) ; extra == 'dev'
Requires-Dist: pytest-cov (==2.11.1) ; extra == 'dev'
Requires-Dist: pytest-sugar (==0.9.4) ; extra == 'dev'
Requires-Dist: flake8 (==3.8.4) ; extra == 'dev'
Requires-Dist: tox (==3.21.4) ; extra == 'dev'
Provides-Extra: doc
Provides-Extra: test
Requires-Dist: mypy (==0.800) ; extra == 'test'
Requires-Dist: coverage (==5.4) ; extra == 'test'
Requires-Dist: pytest (==6.2.2) ; extra == 'test'
Requires-Dist: pytest-mypy (==0.8.0) ; extra == 'test'
Requires-Dist: pytest-cov (==2.11.1) ; extra == 'test'
Requires-Dist: pytest-sugar (==0.9.4) ; extra == 'test'
